message_flow_rabbitmq-0.2.2.dist-info/METADATA
message_flow_rabbitmq-0.2.2.dist-info/WHEEL
message_flow_rabbitmq-0.2.2.dist-info/licenses/LICENSE
message_flow_rabbitmq/__init__.py
message_flow_rabbitmq/consumer/__init__.py
message_flow_rabbitmq/consumer/_consumer_construction.py
message_flow_rabbitmq/consumer/amqp_data.py
message_flow_rabbitmq/consumer/consumer.py
message_flow_rabbitmq/consumer/dead_letters/__init__.py
message_flow_rabbitmq/consumer/dead_letters/dead_letters.py
message_flow_rabbitmq/consumer/dead_letters/dead_letters_config.py
message_flow_rabbitmq/consumer/handler.py
message_flow_rabbitmq/consumer/subscription.py
message_flow_rabbitmq/producer/__init__.py
message_flow_rabbitmq/producer/_producer_construction.py
message_flow_rabbitmq/producer/producer.py
message_flow_rabbitmq/retry_manager/__init__.py
message_flow_rabbitmq/retry_manager/reconnecting_error.py
message_flow_rabbitmq/retry_manager/retry_config.py
message_flow_rabbitmq/retry_manager/retry_manager.py
message_flow_rabbitmq-0.2.2.dist-info/RECORD
