Metadata-Version: 2.1
Name: message-flow-rabbitmq
Version: 0.2.2
Summary: RabbitMQ messaging for the Message Flow
Author-Email: Valentin Vorobyev <voro6yov.valentin@gmail.com>
License: Apache License 2.0
Requires-Python: >=3.10
Requires-Dist: pika>=1.3.2
Requires-Dist: click>=8.1.7; extra == "local-run"
Provides-Extra: local-run
